sila2/__init__.py
sila2/config.py
sila2/py.typed
sila2/client/__init__.py
sila2/client/client_feature.py
sila2/client/client_metadata.py
sila2/client/client_observable_command.py
sila2/client/client_observable_command_instance.py
sila2/client/client_observable_property.py
sila2/client/client_unobservable_command.py
sila2/client/client_unobservable_property.py
sila2/client/execution_info_subscription_thread.py
sila2/client/grpc_stream_subscription.py
sila2/client/polling_subscription.py
sila2/client/sila_client.py
sila2/client/subscription.py
sila2/client/utils.py
sila2/code_generator/__init__.py
sila2/code_generator/__main__.py
sila2/code_generator/code_generator.py
sila2/code_generator/code_generator_base.py
sila2/code_generator/feature_generator.py
sila2/code_generator/template_environment.py
sila2/code_generator/template_loader.py
sila2/code_generator/template_objects/__init__.py
sila2/code_generator/template_objects/base.py
sila2/code_generator/template_objects/basics.py
sila2/code_generator/template_objects/client.py
sila2/code_generator/template_objects/types.py
sila2/discovery/__init__.py
sila2/discovery/broadcaster.py
sila2/discovery/browser.py
sila2/discovery/listener.py
sila2/discovery/service_info.py
sila2/features/__init__.py
sila2/features/authenticationservice/AuthenticationService.sila.xml
sila2/features/authenticationservice/__init__.py
sila2/features/authenticationservice/authenticationservice_base.py
sila2/features/authenticationservice/authenticationservice_client.py
sila2/features/authenticationservice/authenticationservice_errors.py
sila2/features/authenticationservice/authenticationservice_feature.py
sila2/features/authenticationservice/authenticationservice_types.py
sila2/features/authorizationproviderservice/AuthorizationProviderService.sila.xml
sila2/features/authorizationproviderservice/__init__.py
sila2/features/authorizationproviderservice/authorizationproviderservice_base.py
sila2-0.13.0.dist-info/LICENSE
sila2-0.13.0.dist-info/METADATA
sila2-0.13.0.dist-info/WHEEL
sila2-0.13.0.dist-info/entry_points.txt
sila2-0.13.0.dist-info/top_level.txt
sila2-0.13.0.dist-info/RECORD
