Metadata-Version: 2.1
Name: sila2
Version: 0.13.0
Summary: Python implementation of the SiLA 2 standard for lab automation
Author-email: Niklas Mertsch <niklas.mertsch@wega-it.com>
License: MIT License
Project-URL: Homepage, https://gitlab.com/sila2/sila_python
Project-URL: Repository, https://gitlab.com/sila2/sila_python
Project-URL: Documentation, https://sila2.gitlab.io/sila_python
Project-URL: Bug Tracker, https://gitlab.com/sila2/sila_python/-/issues
Project-URL: SiLA Standard, https://sila-standard.org
Classifier: Development Status :: 4 - Beta
Classifier: Intended Audience :: Developers
Classifier: Intended Audience :: Science/Research
Classifier: Intended Audience :: Healthcare Industry
Classifier: License :: OSI Approved :: MIT License
Classifier: Operating System :: OS Independent
Classifier: Programming Language :: Python :: 3
Requires-Python: >=3.8
License-File: LICENSE
Requires-Dist: grpcio >=1.44.0
Requires-Dist: grpcio-tools >=1.44.0
Requires-Dist: lxml >=4.4.0
Requires-Dist: typing-extensions
Requires-Dist: zeroconf
Provides-Extra: codegen
Requires-Dist: black ; extra == 'codegen'
Requires-Dist: isort ; extra == 'codegen'
Requires-Dist: jinja2 ; extra == 'codegen'
Requires-Dist: typer ; extra == 'codegen'
Provides-Extra: cryptography
Requires-Dist: cryptography >=36.0.0 ; extra == 'cryptography'
Provides-Extra: dev
Requires-Dist: grpcio-testing ; extra == 'dev'
Requires-Dist: ruff ; extra == 'dev'
Requires-Dist: pytest ; extra == 'dev'
Requires-Dist: pytest-cov ; extra == 'dev'
Requires-Dist: semgrep ; extra == 'dev'
Provides-Extra: docs
Requires-Dist: sphinx ; extra == 'docs'
Requires-Dist: sphinxcontrib-runcmd ; extra == 'docs'
Requires-Dist: furo ; extra == 'docs'
Provides-Extra: full
Requires-Dist: black ; extra == 'full'
Requires-Dist: cryptography >=36.0.0 ; extra == 'full'
Requires-Dist: grpcio-testing ; extra == 'full'
Requires-Dist: isort ; extra == 'full'
Requires-Dist: jinja2 ; extra == 'full'
Requires-Dist: jsonschema ; extra == 'full'
Requires-Dist: pytest ; extra == 'full'
Requires-Dist: pytest-cov ; extra == 'full'
Requires-Dist: ruff ; extra == 'full'
Requires-Dist: sphinx ; extra == 'full'
Requires-Dist: sphinxcontrib-runcmd ; extra == 'full'
Requires-Dist: furo ; extra == 'full'
Requires-Dist: typer ; extra == 'full'
Requires-Dist: xmlschema ; extra == 'full'
Requires-Dist: semgrep ; (platform_system != "Windows") and extra == 'full'
Provides-Extra: jsonschema
Requires-Dist: jsonschema ; extra == 'jsonschema'
Provides-Extra: test
Requires-Dist: grpcio-testing ; extra == 'test'
Requires-Dist: pytest ; extra == 'test'
Requires-Dist: pytest-cov ; extra == 'test'
Provides-Extra: xmlschema
Requires-Dist: xmlschema ; extra == 'xmlschema'
